aoe2rec_py-0.1.18.dist-info/METADATA
aoe2rec_py-0.1.18.dist-info/WHEEL
aoe2rec_py.libs/libgcc_s-0366c7ba.so.1
aoe2rec_py/__init__.py
aoe2rec_py/aoe2rec_py.pypy311-pp73-arm-linux-gnu.so
aoe2rec_py/summary.py
aoe2rec_py-0.1.18.dist-info/RECORD
